fpob/utils/__init__.py
fpob/utils/concurrency.py
fpob/utils/lists.py
fpob/utils/py.typed
fpob/utils/sensible.py
fpob.utils-2.0.0.dist-info/LICENSE
fpob.utils-2.0.0.dist-info/WHEEL
fpob.utils-2.0.0.dist-info/METADATA
fpob.utils-2.0.0.dist-info/RECORD
